2048_cli-1.0.3.dist-info/METADATA
2048_cli-1.0.3.dist-info/WHEEL
2048_cli-1.0.3.dist-info/entry_points.txt
src/main.py
src/ai_playing/benchmark.py
src/ai_playing/montecarlo.py
src/game.py
src/utils.py
src/rust-montecarlo/lib.rs
src/rust-montecarlo/board.rs
src/board.py
src/rust_montecarlo.cpython-312-x86_64-linux-gnu.so
2048_cli-1.0.3.dist-info/RECORD
