Metadata-Version: 2.3
Name: 2048-cli
Version: 1.0.3
Classifier: Environment :: Console
Classifier: Programming Language :: Rust
Classifier: Topic :: Games/Entertainment
Requires-Dist: numpy >=1.23.3
Requires-Dist: click >=8.1.3
Requires-Dist: rich >=13.7.0
Requires-Dist: rich-menu >=0.1.4
Requires-Dist: maturin >=1.4.0
Summary: A small clone of 2048 for terminal, and also the implementation of an A.I. for it
Author-email: gbPagano <guilhermebpagano@gmail.com>
Requires-Python: >=3.10
Project-URL: Source Code, https://github.com/gbPagano/2048-cli
Project-URL: Issues, https://github.com/gbPagano/2048-cli/issues
